[
  {
    "id": "Q1-GEN-V83-01",
    "chapter": "第1章",
    "level": "K3",
    "category": "一般",
    "style": "シナリオ",
    "type": "単一選択",
    "question": "【適用】不十分な終了基準への対応。\nテスト計画書に定義された終了基準が「テスト実行率100%」のみであり、品質リスクに関する基準が含まれていないことに気づいた。\nテスト実行は完了したが、重大な欠陥が未解決のまま残っている。\nこの状況でテストマネージャが取るべき行動は？",
    "options": [
      "計画書通り「実行率100%」なので完了とし、リリースを承認する",
      "独断でリリースを拒否する",
      "ステークホルダーに対して「現在の基準（実行率のみ）では品質リスク（未解決欠陥）をカバーできていない」ことを報告し、終了基準の追加（欠陥ゼロ等）またはリスク受容の合意形成を行う",
      "開発者に修正を強制する"
    ],
    "answer": [
      "ステークホルダーに対して「現在の基準（実行率のみ）では品質リスク（未解決欠陥）をカバーできていない」ことを報告し、終了基準の追加（欠陥ゼロ等）またはリスク受容の合意形成を行う"
    ],
    "explanation": "【解説】\n不十分な基準に従ってリリースし、市場障害を起こすのはマネジメントの失敗です。リスクを可視化し、基準の再定義（または特例承認）を促すのが正しいアクションです。",
    "tags": [
      "第1章",
      "一般",
      "シナリオ",
      "K3"
    ]
  },
  {
    "id": "Q1-GEN-V83-02",
    "chapter": "第1章",
    "level": "K3",
    "category": "一般",
    "style": "シナリオ",
    "type": "単一選択",
    "question": "【適用】テスト自動化の失敗からのリカバリ。\n「全テストケースの自動化」を目標に掲げたが、メンテナンス工数が肥大化し、テスト実行が滞っている。\nこの状況を改善するための戦略的転換（ピボット）として最も適切なものは？",
    "options": [
      "人員を倍増してメンテナンスする",
      "自動化のスコープを「スモークテスト」や「安定した機能の回帰テスト」に絞り込み、変更頻度が高い部分や探索的テストが必要な部分は手動に戻す",
      "自動化を完全に中止し、全て手動に戻す",
      "自動テストはコストに見合わないと判断して全廃し、すべて手動テストに戻す"
    ],
    "answer": [
      "自動化のスコープを「スモークテスト」や「安定した機能の回帰テスト」に絞り込み、変更頻度が高い部分や探索的テストが必要な部分は手動に戻す"
    ],
    "explanation": "【解説】\n「全自動化」は多くの場合、失敗します。ROIが高い領域（繰り返し実行され、変更が少ない部分）に絞ることが、持続可能な自動化の鍵です。",
    "tags": [
      "第1章",
      "一般",
      "シナリオ",
      "K3"
    ]
  }
]