[
  {
    "id": "Q1-AWS-V136-01",
    "chapter": "第1章",
    "level": "K3",
    "category": "AWS",
    "style": "シナリオ",
    "type": "単一選択",
    "question": "【適用】CloudWatch Logsのリアルタイム監視。\nアプリケーションログの中に「ERROR」という文字列が出力されたら、即座にLambda関数を起動してSlackに通知を送りたい。\nこれを実現するための最も低遅延かつ標準的なAWS構成はどれか。",
    "options": [
      "CloudWatch Logsに「サブスクリプションフィルタ」を設定し、ログイベントを直接Lambda関数にストリーミングして、Lambda内でキーワード判定と通知を行う",
      "Lambda関数を5分ごとにスケジュール実行（cron）し、CloudWatch LogsのAPIを呼び出して過去5分間のログを検索（FilterLogEvents）する",
      "S3バケットへのログエクスポートを設定し、S3にファイルが保存されたイベント（PutObject）をトリガーにLambdaを起動してファイルの中身を解析する",
      "EC2インスタンス内に監視エージェントを自作して常駐させ、ログファイルを tail -f で監視して、エラーが出たらメールコマンドを実行する"
    ],
    "answer": [
      "CloudWatch Logsに「サブスクリプションフィルタ」を設定し、ログイベントを直接Lambda関数にストリーミングして、Lambda内でキーワード判定と通知を行う"
    ],
    "explanation": "【解説】\nログのリアルタイム処理には「サブスクリプションフィルタ」を使用します。ログ取り込みとほぼ同時にLambdaへデータをプッシュできるため、ポーリングやバッチ処理よりも即応性が高いです。",
    "tags": [
      "第1章",
      "AWS",
      "シナリオ",
      "K3"
    ]
  }
]