[
  {
    "id": "Q2-MED-V2-01",
    "chapter": "第2章",
    "level": "K3",
    "category": "医療",
    "style": "シナリオ",
    "type": "単一選択",
    "question": "【背景】医療機器のユーザビリティテスト。【課題】最も重視すべき参加者は？",
    "options": [
      "システムの内部仕様を熟知しており、迷わずスムーズな操作が可能な開発エンジニア",
      "実際のユーザー層（医師、看護師、患者）に近い属性を持ち、システムに慣れていない人",
      "医療機器規制（FDA等）の条文には詳しいが、機器の操作は未経験の法務・知財担当者",
      "購入の意思決定権を持つが、実際の操作は行わない病院の事務長や理事長"
    ],
    "answer": [
      "実際のユーザー層（医師、看護師、患者）に近い属性を持ち、システムに慣れていない人"
    ],
    "explanation": "想定ユーザーの実際の利用環境での誤操作リスクを検証する必要があります。"
  }
]