[
  {
    "id": "Q2-CLD-01",
    "chapter": "第2章",
    "level": "K2",
    "category": "クラウド",
    "style": "用語",
    "type": "単一選択",
    "question": "クラウド品質指標は？",
    "options": [
      "SLA（サービスレベル合意）およびSLO",
      "WBS（Work Breakdown Structure）の進捗率",
      "LOC（Lines of Code）と循環的複雑度",
      "開発チームの平均年齢と経験年数"
    ],
    "answer": [
      "SLA（サービスレベル合意）およびSLO"
    ],
    "explanation": "サービスレベル合意/目標。"
  },
  {
    "id": "Q2-CLD-02",
    "chapter": "第2章",
    "level": "K2",
    "category": "クラウド",
    "style": "用語",
    "type": "単一選択",
    "question": "マルチテナント環境での重要品質特性は？",
    "options": [
      "分離性（Isolation）：あるテナントの負荷やデータ漏洩が他テナントに影響しないこと",
      "カスタマイズ性：各テナントが自由にソースコードを書き換えられること",
      "インストール性：ユーザーのPCに専用クライアントを導入しやすいこと",
      "魅力性：画面デザインが洗練されており、ユーザーを惹きつけること"
    ],
    "answer": [
      "分離性（Isolation）：あるテナントの負荷やデータ漏洩が他テナントに影響しないこと"
    ],
    "explanation": "あるテナントの負荷やデータが他テナントに影響しないこと（ノイジーネイバー問題など）。"
  },
  {
    "id": "Q2-CLD-03",
    "chapter": "第2章",
    "level": "K3",
    "category": "クラウド",
    "style": "シナリオ",
    "type": "単一選択",
    "question": "【背景】API公開。【課題】セキュリティレビューの観点は？",
    "options": [
      "認証・認可の不備、レート制限（DoS対策）、インジェクション脆弱性",
      "APIのエンドポイントURLの命名規則がRESTfulであるか",
      "レスポンスのJSONが見やすく整形（Pretty Print）されているか",
      "APIドキュメントのフォントサイズや配色が見やすいか"
    ],
    "answer": [
      "認証・認可の不備、レート制限（DoS対策）、インジェクション脆弱性"
    ],
    "explanation": "公開APIは攻撃対象になりやすいため、アクセス制御と負荷対策が必須です。"
  },
  {
    "id": "Q2-CLD-04",
    "chapter": "第2章",
    "level": "K2",
    "category": "クラウド",
    "style": "用語",
    "type": "単一選択",
    "question": "「ポータビリティ（移植性）」のクラウドにおける意味は？",
    "options": [
      "モバイル端末（スマホ・タブレット）での表示崩れがないこと",
      "オンプレミスや他クラウドへの移行容易性",
      "特定クラウドベンダーの独自機能（プロプライエタリなサービス）にフル依存し、他社への移行性（ポータビリティ）を考慮しない",
      "アプリケーションの動作が軽量で高速であること"
    ],
    "answer": [
      "オンプレミスや他クラウドへの移行容易性"
    ],
    "explanation": "コンテナ技術などが寄与する特性です。"
  },
  {
    "id": "Q2-CLD-05",
    "chapter": "第2章",
    "level": "K2",
    "category": "クラウド",
    "style": "用語",
    "type": "単一選択",
    "question": "Observability（可観測性）を構成する3要素は？",
    "options": [
      "ログ、メトリクス、トレース",
      "CPU、メモリ、ディスク",
      "計画、実行、報告",
      "赤、青、緑"
    ],
    "answer": [
      "ログ、メトリクス、トレース"
    ],
    "explanation": "分散システムの状態を外部出力から推測するための3本柱です。"
  }
]