[
  {
    "id": "Q2-GEN-V90-01",
    "chapter": "第2章",
    "level": "K3",
    "category": "一般",
    "style": "シナリオ",
    "type": "単一選択",
    "question": "【分析】レビューメトリクスの評価。\nある設計書のインスペクションを実施した。\n・準備（予習）時間：平均 10ページ/時間\n・会議時間：平均 2ページ/時間\n・発見欠陥数：0件\n\nこの結果に対する評価として最も疑わしい（リスクが高い）状況は？",
    "options": [
      "準備速度（10ページ/時）が速すぎて十分に読めておらず、かつ会議も慎重すぎて進んでいない、または誰も欠陥を見つけられずに沈黙している可能性がある",
      "非常に効率的にレビューが行われており、品質が高い状態である",
      "準備時間は適切だが、会議時間が長すぎるため、ファシリテーションに問題がある",
      "欠陥が0件なのは設計品質が完璧である証拠なので、何も問題はない"
    ],
    "answer": [
      "準備速度（10ページ/時）が速すぎて十分に読めておらず、かつ会議も慎重すぎて進んでいない、または誰も欠陥を見つけられずに沈黙している可能性がある"
    ],
    "explanation": "【解説】\n準備速度が推奨値（5ページ前後）より速いのに欠陥ゼロというのは、読み飛ばしの可能性が高いです。会議速度が遅いのも、理解不足による停滞を示唆しています。",
    "tags": [
      "第2章",
      "一般",
      "シナリオ",
      "K3"
    ]
  },
  {
    "id": "Q2-GEN-V90-02",
    "chapter": "第2章",
    "level": "K3",
    "category": "一般",
    "style": "シナリオ",
    "type": "単一選択",
    "question": "【計算】予防コストへの投資判断。\n「テスト担当者への教育（単価50万円）」を実施することで、テスト設計のミスによる「手戻りコスト（1件あたり10万円）」を削減したい。\n教育を実施することで、手戻りが「10件」減ると予測される場合、この投資は妥当か？",
    "options": [
      "妥当である（ROIがプラスになるため）",
      "妥当ではない（ROIがマイナスになるため）",
      "どちらとも言えない",
      "教育はコストではなく投資なので無条件に実施すべき"
    ],
    "answer": [
      "妥当である"
    ],
    "explanation": "【解説】\n削減額 = 10件 × 10万円 = 100万円。\n投資額 = 50万円。\n利益 = 100万 - 50万 = 50万円。ROIはプラスなので妥当です。",
    "tags": [
      "第2章",
      "一般",
      "シナリオ",
      "K3"
    ]
  }
]