[
  {
    "id": "Q2-GEN-V10-01",
    "chapter": "第2章",
    "level": "K4",
    "category": "一般",
    "style": "シナリオ",
    "type": "単一選択",
    "question": "【背景】ODC（直交欠陥分類）分析。テスト工程の後半になっても「機能欠落（Function Missing）」タイプの欠陥が多く検出されている。\n【分析】このデータが示唆するプロセス上の弱点は？",
    "options": [
      "コーディングミスが多い",
      "要件定義や基本設計のレビューが不十分で、仕様漏れが下流まで流出している",
      "テストケースが細かすぎる",
      "性能テストが不足している"
    ],
    "answer": [
      "要件定義や基本設計のレビューが不十分で、仕様漏れが下流まで流出している"
    ],
    "explanation": "「機能がない」というバグは、実装ミスではなく設計・要件の不備に起因することが多く、上流工程の改善が必要です。"
  },
  {
    "id": "Q2-GEN-V10-02",
    "chapter": "第2章",
    "level": "K4",
    "category": "一般",
    "style": "シナリオ",
    "type": "複数選択",
    "question": "【背景】静的解析ツール導入後、警告（Warning）が数千件発生し、開発者が無視し始めた。\n【課題】品質文化を醸成するための導入戦略として適切なものを2つ選べ。",
    "options": [
      "「新規に追加・変更したコード」のみをチェック対象とし、既存コードの警告はベースラインとして一旦許容する（ラットチェット運用）",
      "全ての警告を解消するまでコミットを禁止する",
      "重大度（Severity）の高い警告のみをブロック対象とし、軽微なものは情報通知に留める",
      "ツールをアンインストールする"
    ],
    "answer": [
      "「新規に追加・変更したコード」のみをチェック対象とし、既存コードの警告はベースラインとして一旦許容する（ラットチェット運用）",
      "重大度（Severity）の高い警告のみをブロック対象とし、軽微なものは情報通知に留める"
    ],
    "explanation": "いきなり完璧を目指すと破綻します。「悪化させない（新規のみ）」や「重要度で絞る」段階的な適用が定石です。"
  }
]