[
  {
    "id": "Q2-GEN-V67-01",
    "chapter": "第2章",
    "level": "K2",
    "category": "一般",
    "style": "用語",
    "type": "単一選択",
    "question": "レビュー計画を作成する前に、レビューリーダ（マネージャ）が考慮すべき要素として適切でないものはどれか。",
    "options": [
      "レビュー対象となるプロダクトおよびプロセス",
      "レビューの投資効果（ROI）やリスク要因",
      "レビューに関与する人物",
      "レビューアの個人的なスケジュール都合"
    ],
    "answer": [
      "レビューアの個人的なスケジュール都合"
    ],
    "explanation": "【解説】\nレビュー計画では「何（対象）を」「誰（参加者）が」「なぜ（リスク・ROI）」レビューするかを考慮して、最適なレビュータイプや予算を決定します。",
    "tags": [
      "第2章",
      "一般",
      "用語",
      "K2"
    ]
  },
  {
    "id": "Q2-GEN-V67-02",
    "chapter": "第2章",
    "level": "K2",
    "category": "一般",
    "style": "用語",
    "type": "単一選択",
    "question": "「欠陥マネジメントツール」が提供できる情報（メトリクス）として、最も典型的なものはどれか。",
    "options": [
      "システム全体の欠陥のステータス（状態）、重要度、優先度、および分布",
      "コードのサイクロマティック複雑度",
      "システムの応答時間とスループット",
      "要件定義書とテストケースのトレーサビリティ行列"
    ],
    "answer": [
      "システム全体の欠陥のステータス（状態）、重要度、優先度、および分布"
    ],
    "explanation": "【解説】\n欠陥管理ツールはバグの「状態（Open/Fixed/Closed）」や「属性（Severity/Priority）」を可視化します。\n複雑度は静的解析、性能は性能テストツール、トレーサビリティはテスト管理ツールの領分です。",
    "tags": [
      "第2章",
      "一般",
      "用語",
      "K2"
    ]
  }
]