[
  {
    "id": "Q3-MED-V3-01",
    "chapter": "第3章",
    "level": "K3",
    "category": "医療",
    "style": "シナリオ",
    "type": "単一選択",
    "question": "【背景】医療機器開発の新人テスターが「手順書が細かすぎて面倒だ」と不満を漏らしている。【課題】マネージャの説明として適切なものは？",
    "options": [
      "「開発スピードを優先するため、ドキュメント作成は製品リリース後にまとめて行えばよい」と許可する",
      "「規制当局（FDA等）への説明責任を果たすために、プロセス遵守の証拠が必要なんだ。君の作業ログが患者の安全を守る盾になる」と意義を説く",
      "「手順書の作成と維持はテストチームの仕事ではないので、品質保証（QA）部門にすべて一任しよう」と責任を転嫁する",
      "「形式的な手順書は廃止し、アジャイル宣言に従って包括的なドキュメントよりも対話を重視しよう」と誤った解釈を伝える"
    ],
    "answer": [
      "「規制当局（FDA等）への説明責任を果たすために、プロセス遵守の証拠が必要なんだ。君の作業ログが患者の安全を守る盾になる」と意義を説く"
    ],
    "explanation": "単なるルール押し付けではなく、その背景（患者安全・法令遵守）と意義を伝えて動機付けを行うのがマネジメントです。"
  }
]