[
  {
    "id": "Q3-GEN-V128-01",
    "chapter": "第3章",
    "level": "K3",
    "category": "一般",
    "style": "シナリオ",
    "type": "単一選択",
    "question": "【適用】テスト終了基準と残存リスク。\nリリース予定日が迫っているが、優先度「低」のバグが数件修正されずに残っている。\nテスト終了基準（Exit Criteria）としては「重大なバグがないこと」と定義されている。\nテストマネージャが取るべき行動として、最も適切なものはどれか。",
    "options": [
      "残っているバグがシステムの重要機能に影響しないことを確認し、ステークホルダーと合意した上で、残存リスクとして記録してテストを終了する",
      "すべてのバグを修正しない限りリリースは認められないため、独断でリリース延期を決定し、開発チームに徹夜での修正を命じる",
      "優先度「低」のバグであれば顧客に気づかれることはないため、バグ管理システムから削除して「バグゼロ」の状態にしてからリリースする",
      "テスト終了基準を満たしていないが、リリース日は絶対であるため、バグの存在を報告書には記載せず、口頭だけで開発リーダーに伝えてリリースする"
    ],
    "answer": [
      "残っているバグがシステムの重要機能に影響しないことを確認し、ステークホルダーと合意した上で、残存リスクとして記録してテストを終了する"
    ],
    "explanation": "【解説】\nテスト終了は「バグゼロ」を意味しません。終了基準（重大なバグがない）を満たし、残存リスク（既知の軽微なバグ）についてステークホルダーの合意（受容）が得られれば、リリース可能です。",
    "tags": [
      "第3章",
      "一般",
      "シナリオ",
      "K3"
    ]
  }
]