[
  {
    "id": "Q3-GEN-V123-01",
    "chapter": "第3章",
    "level": "K3",
    "category": "一般",
    "style": "シナリオ",
    "type": "単一選択",
    "question": "【適用】テストツールの導入とPoC（概念実証）。\n組織全体に新しいテスト自動化ツールを導入しようと計画している。カタログスペック上は要件を満たしているが、実際の開発プロセスに適合するかは不明である。\n本格導入前のリスク軽減策として、最も適切なアプローチはどれか。",
    "options": [
      "ツールのライセンスを全プロジェクト分一括購入し、トップダウンで「来月から全員このツールを使うこと」という業務命令を出して強制的に定着させる",
      "特定のパイロットプロジェクトを選定してPoC（概念実証）を実施し、実際の環境で期待通りの効果が出るか、既存プロセスと競合しないかを小規模に検証する",
      "ツールのベンダー営業担当者の説明を全面的に信頼し、自社での検証は行わずに、ベンダーが提示した成功事例の数値をそのまま経営層への報告に使う",
      "無料のオープンソースツールであれば導入コストはゼロであるため、検証なしに全社員のPCにインストールさせ、使いながら問題点を見つけてもらう"
    ],
    "answer": [
      "特定のパイロットプロジェクトを選定してPoC（概念実証）を実施し、実際の環境で期待通りの効果が出るか、既存プロセスと競合しないかを小規模に検証する"
    ],
    "explanation": "【解説】\nツール導入の失敗を防ぐにはPoC（Proof of Concept）が不可欠です。スモールスタートで実効性を確認してから、段階的に展開するのが定石です。",
    "tags": [
      "第3章",
      "一般",
      "シナリオ",
      "K3"
    ]
  }
]