[
  {
    "id": "Q3-GEN-V95-01",
    "chapter": "第3章",
    "level": "K2",
    "category": "一般",
    "style": "用語",
    "type": "単一選択",
    "question": "人材育成における「メンタリング（Mentoring）」と「コーチング（Coaching）」の違いとして、一般的に正しい認識はどれか。",
    "options": [
      "メンタリングは、特定のタスク遂行に必要な技術的スキルを短期間で指導することであり、コーチングは、長期的な視点で人格形成やキャリア開発を支援することである",
      "メンタリングは、経験豊富な先輩（メンター）が、キャリアや個人的な成長を含めて長期的に支援・助言すること。\nコーチングは、具体的なスキルやパフォーマンス向上のために、問いかけを通じて相手の能力を引き出すこと",
      "メンタリングは技術的な指導のみを行い、コーチングは精神的なサポートのみを行う",
      "両者に明確な違いはなく、どちらも上司が部下に対して行う一方的な指導のことである"
    ],
    "answer": [
      "メンタリングは、経験豊富な先輩（メンター）が、キャリアや個人的な成長を含めて長期的に支援・助言すること。\nコーチングは、具体的なスキルやパフォーマンス向上のために、問いかけを通じて相手の能力を引き出すこと"
    ],
    "explanation": "【解説】\n・メンタリング：長期的・包括的・関係性重視。\n・コーチング：タスク指向・パフォーマンス重視。\n状況に応じて使い分けるのがマネジメントスキルです。",
    "tags": [
      "第3章",
      "一般",
      "用語",
      "K2"
    ]
  },
  {
    "id": "Q3-GEN-V95-02",
    "chapter": "第3章",
    "level": "K3",
    "category": "一般",
    "style": "シナリオ",
    "type": "単一選択",
    "question": "【適用】パフォーマンス評価のフィードバック。\n部下のテスターに対して評価面談を行う。彼の実績は「バグ発見数は少ないが、難易度の高い環境構築や自動化スクリプトの保守でチームに貢献した」。\n適切なフィードバックは？",
    "options": [
      "バグ発見数が少ないので評価を下げる",
      "「バグ数」という単一の指標だけで判断せず、環境構築や保守といった「縁の下の力持ち」的な貢献がプロジェクト全体の効率化に寄与したことを具体的に評価し、称賛する",
      "もっとバグを見つけるよう命令する",
      "評価を保留する"
    ],
    "answer": [
      "「バグ数」という単一の指標だけで判断せず、環境構築や保守といった「縁の下の力持ち」的な貢献がプロジェクト全体の効率化に寄与したことを具体的に評価し、称賛する"
    ],
    "explanation": "【解説】\nテストマネージャは、可視化されにくい貢献（予防活動や環境整備）を正当に評価する責任があります。",
    "tags": [
      "第3章",
      "一般",
      "シナリオ",
      "K3"
    ]
  },
  {
    "id": "Q3-GEN-V95-03",
    "chapter": "第3章",
    "level": "K2",
    "category": "一般",
    "style": "用語",
    "type": "単一選択",
    "question": "「ホールチームアプローチ（Whole Team Approach）」を採用しているアジャイルチームにおいて、テスト担当者の主な役割は？",
    "options": [
      "開発が終わるまで待機する",
      "チームから隔離された部屋でテストする",
      "品質に対する責任を一人で負うのではなく、開発者やPOと協調し、チーム全体が品質に責任を持てるように情報提供や支援を行う",
      "品質警察（Quality Police）として振る舞い、開発者のコードの欠点を指摘するだけで改善には関与しない"
    ],
    "answer": [
      "品質に対する責任を一人で負うのではなく、開発者やPOと協調し、チーム全体が品質に責任を持てるように情報提供や支援を行う"
    ],
    "explanation": "【解説】\n「品質は全員の責任」がアジャイルの基本です。テスターはゲートキーパーではなく、品質のファシリテーターとなります。",
    "tags": [
      "第3章",
      "一般",
      "用語",
      "K2"
    ]
  },
  {
    "id": "Q3-GEN-V95-04",
    "chapter": "第3章",
    "level": "K2",
    "category": "一般",
    "style": "用語",
    "type": "単一選択",
    "question": "テストチーム内の「コミュニケーションパス」が増えすぎることによる弊害（ブルックスの法則に関連）はどれか。",
    "options": [
      "情報伝達が速くなる",
      "コミュニケーションのオーバーヘッド（調整コスト）が増大し、生産性が低下する可能性がある",
      "仲良くなれる",
      "ツールが安くなる"
    ],
    "answer": [
      "コミュニケーションのオーバーヘッド（調整コスト）が増大し、生産性が低下する可能性がある"
    ],
    "explanation": "【解説】\n人数(n)が増えるとパスは n(n-1)/2 で指数関数的に増えます。これが大規模チームの効率低下の主因です。",
    "tags": [
      "第3章",
      "一般",
      "用語",
      "K2"
    ]
  }
]