[
  {
    "id": "Q3-GEN-V107-01",
    "chapter": "第3章",
    "level": "K3",
    "category": "一般",
    "style": "シナリオ",
    "type": "単一選択",
    "question": "【適用】テストプロセス改善（TPI Next）の優先順位付け。\n現在のテストプロセスは「場当たり的」で、ドキュメントも標準化されていない。\n限られたリソースで改善を始めるにあたり、最初に手を付けるべきキーエリアとして最も推奨されるものはどれか。",
    "options": [
      "テスト戦略（Strategy）とテスト方法論（Methodology）を定義し、プロジェクト全体で「どのようにテストするか」の共通認識と標準を作る",
      "テスト担当者のスキル評価を行い、スキルの低いメンバーをプロジェクトから外す",
      "詳細なテストケース管理ツールを購入し、すべてのテストケースを細かく記録することを義務付ける",
      "テスト自動化ツールを導入し、手動テストを全て廃止して効率化を図る"
    ],
    "answer": [
      "テスト戦略（Strategy）とテスト方法論（Methodology）を定義し、プロジェクト全体で「どのようにテストするか」の共通認識と標準を作る"
    ],
    "explanation": "【解説】\n改善の初期段階（制御されていない状態）では、まず「標準（どうやるか）」を確立することが最優先です。ツール導入や詳細管理は、プロセスが安定してから行うべきです。",
    "tags": [
      "第3章",
      "一般",
      "シナリオ",
      "K3"
    ]
  }
]